LSH/lsh.py
LSH/numba_helpers.py
LSH/period_based.py
Simple_LSH-1.0.dist-info/LICENSE
Simple_LSH-1.0.dist-info/METADATA
Simple_LSH-1.0.dist-info/WHEEL
Simple_LSH-1.0.dist-info/top_level.txt
Simple_LSH-1.0.dist-info/RECORD
